cloe_metadata/__init__.py
cloe_metadata/base/__init__.py
cloe_metadata/base/base.py
cloe_metadata/base/batch/__init__.py
cloe_metadata/base/batch/batch.py
cloe_metadata/base/batch/batchstep.py
cloe_metadata/base/jobs/__init__.py
cloe_metadata/base/jobs/connections.py
cloe_metadata/base/jobs/db2fs.py
cloe_metadata/base/jobs/exec_sql.py
cloe_metadata/base/jobs/fs2db.py
cloe_metadata/base/jobs/jobs.py
cloe_metadata/base/modeler/__init__.py
cloe_metadata/base/modeler/custom_dataflow/__init__.py
cloe_metadata/base/modeler/custom_dataflow/custom_dataflow.py
cloe_metadata/base/modeler/custom_dataflow/table_mapping.py
cloe_metadata/base/modeler/dataflow/__init__.py
cloe_metadata/base/modeler/dataflow/column_mapping.py
cloe_metadata/base/modeler/dataflow/dataflow.py
cloe_metadata/base/modeler/dataflow/lookup.py
cloe_metadata/base/modeler/dataflow/source_table.py
cloe_metadata/base/modeler/flows.py
cloe_metadata/base/modeler/templates/__init__.py
cloe_metadata/base/modeler/templates/conversion_template.py
cloe_metadata/base/modeler/templates/datatype_template.py
cloe_metadata/base/modeler/templates/sql_template.py
cloe_metadata/base/repository/__init__.py
cloe_metadata/base/repository/data_source_info.py
cloe_metadata/base/repository/database/__init__.py
cloe_metadata/base/repository/database/column.py
cloe_metadata/base/repository/database/database.py
cloe_metadata/base/repository/database/schema.py
cloe_metadata/base/repository/database/table.py
cloe_metadata/base/repository/dataset_type.py
cloe_metadata/base/repository/sourcesystem.py
cloe_metadata/base/repository/tenant.py
cloe_metadata/py.typed
cloe_metadata/shared/__init__.py
cloe_metadata/shared/jobs/__init__.py
cloe_metadata/shared/jobs/db2fs.py
cloe_metadata/shared/jobs/exec_sql.py
cloe_metadata/shared/jobs/fs2db.py
cloe_metadata/shared/modeler/__init__.py
cloe_metadata/shared/modeler/custom_dataflow/__init__.py
cloe_metadata/shared/modeler/custom_dataflow/custom_dataflow.py
cloe_metadata-2.2.7.dist-info/licenses/LICENSE
cloe_metadata-2.2.7.dist-info/WHEEL
cloe_metadata-2.2.7.dist-info/METADATA
cloe_metadata-2.2.7.dist-info/RECORD
