Metadata-Version: 2.4
Name: cloe-metadata
Version: 2.2.7
Summary: Package for all base CLOE metadata objects and support functions.
Keywords: 
Author: initions
Author-email: initions <ICSMC_EXT_PYPIORG@accenture.com>
License-Expression: MIT
License-File: LICENSE
Classifier: Development Status :: 5 - Production/Stable
Classifier: Environment :: Console
Classifier: Intended Audience :: Developers
Classifier: Operating System :: OS Independent
Classifier: Programming Language :: Python :: 3
Classifier: Programming Language :: Python :: 3.11
Classifier: Programming Language :: Python :: 3.12
Classifier: Programming Language :: Python :: 3.13
Classifier: Topic :: Database
Requires-Dist: pydantic~=2.11.9
Requires-Dist: jinja2~=3.1.6
Requires-Dist: croniter~=6.0.0
Requires-Python: >=3.11, <3.14
